niemads/DisjointSet.py
niemads/MultiwayTrie.py
niemads/RandomSet.py
niemads/__init__.py
niemads-1.0.16.dist-info/LICENSE
niemads-1.0.16.dist-info/METADATA
niemads-1.0.16.dist-info/WHEEL
niemads-1.0.16.dist-info/top_level.txt
niemads-1.0.16.dist-info/RECORD
