Metadata-Version: 2.1
Name: niemads
Version: 1.0.16
Summary: NiemaDS: Non-standard data structures for Python 3
Home-page: https://github.com/niemasd/NiemaDS
Author: Niema Moshiri
Author-email: niemamoshiri@gmail.com
Project-URL: Bug Reports, https://github.com/niemasd/NiemaDS/issues
Project-URL: Source, https://github.com/niemasd/NiemaDS
Keywords: data structures fast
Classifier: Development Status :: 3 - Alpha
Classifier: Intended Audience :: Developers
Classifier: Topic :: Software Development :: Build Tools
Classifier: License :: OSI Approved :: GNU General Public License v3 or later (GPLv3+)
Classifier: Programming Language :: Python :: 3
License-File: LICENSE
Provides-Extra: dev
Requires-Dist: check-manifest ; extra == 'dev'
